{".class": "MypyFile", "_fullname": "ibis.expr.window", "is_partial_stub_package": false, "is_stub": false, "names": {".class": "SymbolTable", "NamedTuple": {".class": "SymbolTableNode", "cross_ref": "typing.NamedTuple", "kind": "Gdef"}, "RowsWithMaxLookback": {".class": "SymbolTableNode", "kind": "Gdef", "node": {".class": "TypeInfo", "_promote": null, "abstract_attributes": [], "bases": [{".class": "Instance", "args": [{".class": "UnionType", "items": ["ibis.expr.types.IntervalValue", "builtins.int", {".class": "Instance", "args": [{".class": "AnyType", "missing_import_name": null, "source_any": null, "type_of_any": 4}], "type_ref": "numpy.integer"}]}], "type_ref": "builtins.tuple"}], "declared_metaclass": null, "defn": {".class": "ClassDef", "fullname": "ibis.expr.window.RowsWithMaxLookback", "name": "RowsWithMaxLookback", "type_vars": []}, "flags": ["is_named_tuple"], "fullname": "ibis.expr.window.RowsWithMaxLookback", "metaclass_type": null, "metadata": {"namedtuple": {"fields": ["rows", "max_lookback"]}}, "module_name": "ibis.expr.window", "mro": ["ibis.expr.window.RowsWithMaxLookback", "builtins.tuple", "typing.Sequence", "typing.Collection", "typing.Reversible", "typing.Iterable", "typing.Container", "builtins.object"], "names": {".class": "SymbolTable", "_NT": {".class": "SymbolTableNode", "kind": "Mdef", "node": {".class": "TypeVarExpr", "fullname": "ibis.expr.window.RowsWithMaxLookback._NT", "name": "_NT", "upper_bound": {".class": "TupleType", "implicit": false, "items": [{".class": "UnionType", "items": ["builtins.int", {".class": "Instance", "args": [{".class": "AnyType", "missing_import_name": null, "source_any": null, "type_of_any": 4}], "type_ref": "numpy.integer"}]}, "ibis.expr.types.IntervalValue"], "partial_fallback": {".class": "Instance", "args": [{".class": "UnionType", "items": ["ibis.expr.types.IntervalValue", "builtins.int", {".class": "Instance", "args": [{".class": "AnyType", "missing_import_name": null, "source_any": null, "type_of_any": 4}], "type_ref": "numpy.integer"}]}], "type_ref": "builtins.tuple"}}, "values": [], "variance": 0}}, "__annotations__": {".class": "SymbolTableNode", "kind": "Mdef", "node": {".class": "Var", "flags": ["is_initialized_in_class", "is_ready"], "fullname": "ibis.expr.window.RowsWithMaxLookback.__annotations__", "name": "__annotations__", "type": {".class": "Instance", "args": ["builtins.str", {".class": "AnyType", "missing_import_name": null, "source_any": null, "type_of_any": 6}], "type_ref": "builtins.dict"}}}, "__doc__": {".class": "SymbolTableNode", "kind": "Mdef", "node": {".class": "Var", "flags": ["is_initialized_in_class", "is_ready"], "fullname": "ibis.expr.window.RowsWithMaxLookback.__doc__", "name": "__doc__", "type": "builtins.str"}}, "__new__": {".class": "SymbolTableNode", "kind": "Mdef", "node": {".class": "FuncDef", "arg_kinds": [0, 0, 0], "arg_names": ["_cls", "rows", "max_lookback"], "flags": [], "fullname": "ibis.expr.window.RowsWithMaxLookback.__new__", "name": "__new__", "type": {".class": "CallableType", "arg_kinds": [0, 0, 0], "arg_names": ["_cls", "rows", "max_lookback"], "arg_types": [{".class": "TypeType", "item": {".class": "TypeVarType", "fullname": "ibis.expr.window.RowsWithMaxLookback._NT", "id": -1, "name": "_NT", "upper_bound": {".class": "TupleType", "implicit": false, "items": [{".class": "UnionType", "items": ["builtins.int", {".class": "Instance", "args": [{".class": "AnyType", "missing_import_name": null, "source_any": null, "type_of_any": 4}], "type_ref": "numpy.integer"}]}, "ibis.expr.types.IntervalValue"], "partial_fallback": {".class": "Instance", "args": [{".class": "UnionType", "items": ["ibis.expr.types.IntervalValue", "builtins.int", {".class": "Instance", "args": [{".class": "AnyType", "missing_import_name": null, "source_any": null, "type_of_any": 4}], "type_ref": "numpy.integer"}]}], "type_ref": "builtins.tuple"}}, "values": [], "variance": 0}}, {".class": "UnionType", "items": ["builtins.int", {".class": "Instance", "args": [{".class": "AnyType", "missing_import_name": null, "source_any": null, "type_of_any": 4}], "type_ref": "numpy.integer"}]}, "ibis.expr.types.IntervalValue"], "bound_args": [], "def_extras": {}, "fallback": "builtins.function", "implicit": false, "is_ellipsis_args": false, "name": "__new__ of RowsWithMaxLookback", "ret_type": {".class": "TypeVarType", "fullname": "ibis.expr.window.RowsWithMaxLookback._NT", "id": -1, "name": "_NT", "upper_bound": {".class": "TupleType", "implicit": false, "items": [{".class": "UnionType", "items": ["builtins.int", {".class": "Instance", "args": [{".class": "AnyType", "missing_import_name": null, "source_any": null, "type_of_any": 4}], "type_ref": "numpy.integer"}]}, "ibis.expr.types.IntervalValue"], "partial_fallback": {".class": "Instance", "args": [{".class": "UnionType", "items": ["ibis.expr.types.IntervalValue", "builtins.int", {".class": "Instance", "args": [{".class": "AnyType", "missing_import_name": null, "source_any": null, "type_of_any": 4}], "type_ref": "numpy.integer"}]}], "type_ref": "builtins.tuple"}}, "values": [], "variance": 0}, "variables": [{".class": "TypeVarDef", "fullname": "ibis.expr.window.RowsWithMaxLookback._NT", "id": -1, "name": "_NT", "upper_bound": {".class": "TupleType", "implicit": false, "items": [{".class": "UnionType", "items": ["builtins.int", {".class": "Instance", "args": [{".class": "AnyType", "missing_import_name": null, "source_any": null, "type_of_any": 4}], "type_ref": "numpy.integer"}]}, "ibis.expr.types.IntervalValue"], "partial_fallback": {".class": "Instance", "args": [{".class": "UnionType", "items": ["ibis.expr.types.IntervalValue", "builtins.int", {".class": "Instance", "args": [{".class": "AnyType", "missing_import_name": null, "source_any": null, "type_of_any": 4}], "type_ref": "numpy.integer"}]}], "type_ref": "builtins.tuple"}}, "values": [], "variance": 0}]}}, "plugin_generated": true}, "_asdict": {".class": "SymbolTableNode", "kind": "Mdef", "node": {".class": "FuncDef", "arg_kinds": [0], "arg_names": ["_self"], "flags": [], "fullname": "ibis.expr.window.RowsWithMaxLookback._asdict", "name": "_asdict", "type": {".class": "CallableType", "arg_kinds": [0], "arg_names": ["_self"], "arg_types": [{".class": "TypeVarType", "fullname": "ibis.expr.window.RowsWithMaxLookback._NT", "id": -1, "name": "_NT", "upper_bound": {".class": "TupleType", "implicit": false, "items": [{".class": "UnionType", "items": ["builtins.int", {".class": "Instance", "args": [{".class": "AnyType", "missing_import_name": null, "source_any": null, "type_of_any": 4}], "type_ref": "numpy.integer"}]}, "ibis.expr.types.IntervalValue"], "partial_fallback": {".class": "Instance", "args": [{".class": "UnionType", "items": ["ibis.expr.types.IntervalValue", "builtins.int", {".class": "Instance", "args": [{".class": "AnyType", "missing_import_name": null, "source_any": null, "type_of_any": 4}], "type_ref": "numpy.integer"}]}], "type_ref": "builtins.tuple"}}, "values": [], "variance": 0}], "bound_args": [], "def_extras": {}, "fallback": "builtins.function", "implicit": false, "is_ellipsis_args": false, "name": "_asdict of RowsWithMaxLookback", "ret_type": {".class": "Instance", "args": ["builtins.str", {".class": "AnyType", "missing_import_name": null, "source_any": null, "type_of_any": 6}], "type_ref": "builtins.dict"}, "variables": [{".class": "TypeVarDef", "fullname": "ibis.expr.window.RowsWithMaxLookback._NT", "id": -1, "name": "_NT", "upper_bound": {".class": "TupleType", "implicit": false, "items": [{".class": "UnionType", "items": ["builtins.int", {".class": "Instance", "args": [{".class": "AnyType", "missing_import_name": null, "source_any": null, "type_of_any": 4}], "type_ref": "numpy.integer"}]}, "ibis.expr.types.IntervalValue"], "partial_fallback": {".class": "Instance", "args": [{".class": "UnionType", "items": ["ibis.expr.types.IntervalValue", "builtins.int", {".class": "Instance", "args": [{".class": "AnyType", "missing_import_name": null, "source_any": null, "type_of_any": 4}], "type_ref": "numpy.integer"}]}], "type_ref": "builtins.tuple"}}, "values": [], "variance": 0}]}}, "plugin_generated": true}, "_field_defaults": {".class": "SymbolTableNode", "kind": "Mdef", "node": {".class": "Var", "flags": ["is_initialized_in_class", "is_ready"], "fullname": "ibis.expr.window.RowsWithMaxLookback._field_defaults", "name": "_field_defaults", "type": {".class": "Instance", "args": ["builtins.str", {".class": "AnyType", "missing_import_name": null, "source_any": null, "type_of_any": 6}], "type_ref": "builtins.dict"}}}, "_field_types": {".class": "SymbolTableNode", "kind": "Mdef", "node": {".class": "Var", "flags": ["is_initialized_in_class", "is_ready"], "fullname": "ibis.expr.window.RowsWithMaxLookback._field_types", "name": "_field_types", "type": {".class": "Instance", "args": ["builtins.str", {".class": "AnyType", "missing_import_name": null, "source_any": null, "type_of_any": 6}], "type_ref": "builtins.dict"}}}, "_fields": {".class": "SymbolTableNode", "kind": "Mdef", "node": {".class": "Var", "flags": ["is_initialized_in_class", "is_ready"], "fullname": "ibis.expr.window.RowsWithMaxLookback._fields", "name": "_fields", "type": {".class": "TupleType", "implicit": false, "items": ["builtins.str", "builtins.str"], "partial_fallback": {".class": "Instance", "args": [{".class": "AnyType", "missing_import_name": null, "source_any": null, "type_of_any": 6}], "type_ref": "builtins.tuple"}}}}, "_make": {".class": "SymbolTableNode", "kind": "Mdef", "node": {".class": "Decorator", "func": {".class": "FuncDef", "arg_kinds": [0, 0, 5, 5], "arg_names": ["_cls", "iterable", "new", "len"], "flags": ["is_class", "is_decorated"], "fullname": "ibis.expr.window.RowsWithMaxLookback._make", "name": "_make", "type": {".class": "CallableType", "arg_kinds": [0, 0, 5, 5], "arg_names": ["_cls", "iterable", "new", "len"], "arg_types": [{".class": "TypeType", "item": {".class": "TypeVarType", "fullname": "ibis.expr.window.RowsWithMaxLookback._NT", "id": -1, "name": "_NT", "upper_bound": {".class": "TupleType", "implicit": false, "items": [{".class": "UnionType", "items": ["builtins.int", {".class": "Instance", "args": [{".class": "AnyType", "missing_import_name": null, "source_any": null, "type_of_any": 4}], "type_ref": "numpy.integer"}]}, "ibis.expr.types.IntervalValue"], "partial_fallback": {".class": "Instance", "args": [{".class": "UnionType", "items": ["ibis.expr.types.IntervalValue", "builtins.int", {".class": "Instance", "args": [{".class": "AnyType", "missing_import_name": null, "source_any": null, "type_of_any": 4}], "type_ref": "numpy.integer"}]}], "type_ref": "builtins.tuple"}}, "values": [], "variance": 0}}, {".class": "Instance", "args": [{".class": "AnyType", "missing_import_name": null, "source_any": null, "type_of_any": 6}], "type_ref": "typing.Iterable"}, {".class": "AnyType", "missing_import_name": null, "source_any": null, "type_of_any": 6}, {".class": "AnyType", "missing_import_name": null, "source_any": null, "type_of_any": 6}], "bound_args": [], "def_extras": {}, "fallback": "builtins.function", "implicit": false, "is_ellipsis_args": false, "name": "_make of RowsWithMaxLookback", "ret_type": {".class": "TypeVarType", "fullname": "ibis.expr.window.RowsWithMaxLookback._NT", "id": -1, "name": "_NT", "upper_bound": {".class": "TupleType", "implicit": false, "items": [{".class": "UnionType", "items": ["builtins.int", {".class": "Instance", "args": [{".class": "AnyType", "missing_import_name": null, "source_any": null, "type_of_any": 4}], "type_ref": "numpy.integer"}]}, "ibis.expr.types.IntervalValue"], "partial_fallback": {".class": "Instance", "args": [{".class": "UnionType", "items": ["ibis.expr.types.IntervalValue", "builtins.int", {".class": "Instance", "args": [{".class": "AnyType", "missing_import_name": null, "source_any": null, "type_of_any": 4}], "type_ref": "numpy.integer"}]}], "type_ref": "builtins.tuple"}}, "values": [], "variance": 0}, "variables": [{".class": "TypeVarDef", "fullname": "ibis.expr.window.RowsWithMaxLookback._NT", "id": -1, "name": "_NT", "upper_bound": {".class": "TupleType", "implicit": false, "items": [{".class": "UnionType", "items": ["builtins.int", {".class": "Instance", "args": [{".class": "AnyType", "missing_import_name": null, "source_any": null, "type_of_any": 4}], "type_ref": "numpy.integer"}]}, "ibis.expr.types.IntervalValue"], "partial_fallback": {".class": "Instance", "args": [{".class": "UnionType", "items": ["ibis.expr.types.IntervalValue", "builtins.int", {".class": "Instance", "args": [{".class": "AnyType", "missing_import_name": null, "source_any": null, "type_of_any": 4}], "type_ref": "numpy.integer"}]}], "type_ref": "builtins.tuple"}}, "values": [], "variance": 0}]}}, "is_overload": false, "var": {".class": "Var", "flags": ["is_classmethod", "is_ready"], "fullname": "ibis.expr.window.RowsWithMaxLookback._make", "name": "_make", "type": {".class": "CallableType", "arg_kinds": [0, 0, 5, 5], "arg_names": ["_cls", "iterable", "new", "len"], "arg_types": [{".class": "TypeType", "item": {".class": "TypeVarType", "fullname": "ibis.expr.window.RowsWithMaxLookback._NT", "id": -1, "name": "_NT", "upper_bound": {".class": "TupleType", "implicit": false, "items": [{".class": "UnionType", "items": ["builtins.int", {".class": "Instance", "args": [{".class": "AnyType", "missing_import_name": null, "source_any": null, "type_of_any": 4}], "type_ref": "numpy.integer"}]}, "ibis.expr.types.IntervalValue"], "partial_fallback": {".class": "Instance", "args": [{".class": "UnionType", "items": ["ibis.expr.types.IntervalValue", "builtins.int", {".class": "Instance", "args": [{".class": "AnyType", "missing_import_name": null, "source_any": null, "type_of_any": 4}], "type_ref": "numpy.integer"}]}], "type_ref": "builtins.tuple"}}, "values": [], "variance": 0}}, {".class": "Instance", "args": [{".class": "AnyType", "missing_import_name": null, "source_any": null, "type_of_any": 6}], "type_ref": "typing.Iterable"}, {".class": "AnyType", "missing_import_name": null, "source_any": null, "type_of_any": 6}, {".class": "AnyType", "missing_import_name": null, "source_any": null, "type_of_any": 6}], "bound_args": [], "def_extras": {}, "fallback": "builtins.function", "implicit": false, "is_ellipsis_args": false, "name": "_make of RowsWithMaxLookback", "ret_type": {".class": "TypeVarType", "fullname": "ibis.expr.window.RowsWithMaxLookback._NT", "id": -1, "name": "_NT", "upper_bound": {".class": "TupleType", "implicit": false, "items": [{".class": "UnionType", "items": ["builtins.int", {".class": "Instance", "args": [{".class": "AnyType", "missing_import_name": null, "source_any": null, "type_of_any": 4}], "type_ref": "numpy.integer"}]}, "ibis.expr.types.IntervalValue"], "partial_fallback": {".class": "Instance", "args": [{".class": "UnionType", "items": ["ibis.expr.types.IntervalValue", "builtins.int", {".class": "Instance", "args": [{".class": "AnyType", "missing_import_name": null, "source_any": null, "type_of_any": 4}], "type_ref": "numpy.integer"}]}], "type_ref": "builtins.tuple"}}, "values": [], "variance": 0}, "variables": [{".class": "TypeVarDef", "fullname": "ibis.expr.window.RowsWithMaxLookback._NT", "id": -1, "name": "_NT", "upper_bound": {".class": "TupleType", "implicit": false, "items": [{".class": "UnionType", "items": ["builtins.int", {".class": "Instance", "args": [{".class": "AnyType", "missing_import_name": null, "source_any": null, "type_of_any": 4}], "type_ref": "numpy.integer"}]}, "ibis.expr.types.IntervalValue"], "partial_fallback": {".class": "Instance", "args": [{".class": "UnionType", "items": ["ibis.expr.types.IntervalValue", "builtins.int", {".class": "Instance", "args": [{".class": "AnyType", "missing_import_name": null, "source_any": null, "type_of_any": 4}], "type_ref": "numpy.integer"}]}], "type_ref": "builtins.tuple"}}, "values": [], "variance": 0}]}}}, "plugin_generated": true}, "_replace": {".class": "SymbolTableNode", "kind": "Mdef", "node": {".class": "FuncDef", "arg_kinds": [0, 5, 5], "arg_names": ["_self", "rows", "max_lookback"], "flags": [], "fullname": "ibis.expr.window.RowsWithMaxLookback._replace", "name": "_replace", "type": {".class": "CallableType", "arg_kinds": [0, 5, 5], "arg_names": ["_self", "rows", "max_lookback"], "arg_types": [{".class": "TypeVarType", "fullname": "ibis.expr.window.RowsWithMaxLookback._NT", "id": -1, "name": "_NT", "upper_bound": {".class": "TupleType", "implicit": false, "items": [{".class": "UnionType", "items": ["builtins.int", {".class": "Instance", "args": [{".class": "AnyType", "missing_import_name": null, "source_any": null, "type_of_any": 4}], "type_ref": "numpy.integer"}]}, "ibis.expr.types.IntervalValue"], "partial_fallback": {".class": "Instance", "args": [{".class": "UnionType", "items": ["ibis.expr.types.IntervalValue", "builtins.int", {".class": "Instance", "args": [{".class": "AnyType", "missing_import_name": null, "source_any": null, "type_of_any": 4}], "type_ref": "numpy.integer"}]}], "type_ref": "builtins.tuple"}}, "values": [], "variance": 0}, {".class": "UnionType", "items": ["builtins.int", {".class": "Instance", "args": [{".class": "AnyType", "missing_import_name": null, "source_any": null, "type_of_any": 4}], "type_ref": "numpy.integer"}]}, "ibis.expr.types.IntervalValue"], "bound_args": [], "def_extras": {}, "fallback": "builtins.function", "implicit": false, "is_ellipsis_args": false, "name": "_replace of RowsWithMaxLookback", "ret_type": {".class": "TypeVarType", "fullname": "ibis.expr.window.RowsWithMaxLookback._NT", "id": -1, "name": "_NT", "upper_bound": {".class": "TupleType", "implicit": false, "items": [{".class": "UnionType", "items": ["builtins.int", {".class": "Instance", "args": [{".class": "AnyType", "missing_import_name": null, "source_any": null, "type_of_any": 4}], "type_ref": "numpy.integer"}]}, "ibis.expr.types.IntervalValue"], "partial_fallback": {".class": "Instance", "args": [{".class": "UnionType", "items": ["ibis.expr.types.IntervalValue", "builtins.int", {".class": "Instance", "args": [{".class": "AnyType", "missing_import_name": null, "source_any": null, "type_of_any": 4}], "type_ref": "numpy.integer"}]}], "type_ref": "builtins.tuple"}}, "values": [], "variance": 0}, "variables": [{".class": "TypeVarDef", "fullname": "ibis.expr.window.RowsWithMaxLookback._NT", "id": -1, "name": "_NT", "upper_bound": {".class": "TupleType", "implicit": false, "items": [{".class": "UnionType", "items": ["builtins.int", {".class": "Instance", "args": [{".class": "AnyType", "missing_import_name": null, "source_any": null, "type_of_any": 4}], "type_ref": "numpy.integer"}]}, "ibis.expr.types.IntervalValue"], "partial_fallback": {".class": "Instance", "args": [{".class": "UnionType", "items": ["ibis.expr.types.IntervalValue", "builtins.int", {".class": "Instance", "args": [{".class": "AnyType", "missing_import_name": null, "source_any": null, "type_of_any": 4}], "type_ref": "numpy.integer"}]}], "type_ref": "builtins.tuple"}}, "values": [], "variance": 0}]}}, "plugin_generated": true}, "_source": {".class": "SymbolTableNode", "kind": "Mdef", "node": {".class": "Var", "flags": ["is_initialized_in_class", "is_ready"], "fullname": "ibis.expr.window.RowsWithMaxLookback._source", "name": "_source", "type": "builtins.str"}}, "max_lookback": {".class": "SymbolTableNode", "kind": "Mdef", "node": {".class": "Var", "flags": ["is_property", "is_ready"], "fullname": "ibis.expr.window.RowsWithMaxLookback.max_lookback", "name": "max_lookback", "type": "ibis.expr.types.IntervalValue"}}, "rows": {".class": "SymbolTableNode", "kind": "Mdef", "node": {".class": "Var", "flags": ["is_property", "is_ready"], "fullname": "ibis.expr.window.RowsWithMaxLookback.rows", "name": "rows", "type": {".class": "UnionType", "items": ["builtins.int", {".class": "Instance", "args": [{".class": "AnyType", "missing_import_name": null, "source_any": null, "type_of_any": 4}], "type_ref": "numpy.integer"}]}}}}, "tuple_type": {".class": "TupleType", "implicit": false, "items": [{".class": "UnionType", "items": ["builtins.int", {".class": "Instance", "args": [{".class": "AnyType", "missing_import_name": null, "source_any": null, "type_of_any": 4}], "type_ref": "numpy.integer"}]}, "ibis.expr.types.IntervalValue"], "partial_fallback": {".class": "Instance", "args": [{".class": "UnionType", "items": ["ibis.expr.types.IntervalValue", "builtins.int", {".class": "Instance", "args": [{".class": "AnyType", "missing_import_name": null, "source_any": null, "type_of_any": 4}], "type_ref": "numpy.integer"}]}], "type_ref": "builtins.tuple"}}, "type_vars": [], "typeddict_type": null}}, "Union": {".class": "SymbolTableNode", "cross_ref": "typing.Union", "kind": "Gdef"}, "Window": {".class": "SymbolTableNode", "kind": "Gdef", "node": {".class": "TypeInfo", "_promote": null, "abstract_attributes": [], "bases": ["builtins.object"], "declared_metaclass": null, "defn": {".class": "ClassDef", "fullname": "ibis.expr.window.Window", "name": "Window", "type_vars": []}, "flags": [], "fullname": "ibis.expr.window.Window", "metaclass_type": null, "metadata": {}, "module_name": "ibis.expr.window", "mro": ["ibis.expr.window.Window", "builtins.object"], "names": {".class": "SymbolTable", "__hash__": {".class": "SymbolTableNode", "kind": "Mdef", "node": {".class": "FuncDef", "arg_kinds": [0], "arg_names": ["self"], "flags": [], "fullname": "ibis.expr.window.Window.__hash__", "name": "__hash__", "type": {".class": "CallableType", "arg_kinds": [0], "arg_names": ["self"], "arg_types": ["ibis.expr.window.Window"], "bound_args": [], "def_extras": {"first_arg": "self"}, "fallback": "builtins.function", "implicit": false, "is_ellipsis_args": false, "name": "__hash__ of Window", "ret_type": "builtins.int", "variables": []}}}, "__init__": {".class": "SymbolTableNode", "kind": "Mdef", "node": {".class": "FuncDef", "arg_kinds": [0, 1, 1, 1, 1, 1, 1], "arg_names": ["self", "group_by", "order_by", "preceding", "following", "max_lookback", "how"], "flags": [], "fullname": "ibis.expr.window.Window.__init__", "name": "__init__", "type": null}}, "_group_by": {".class": "SymbolTableNode", "implicit": true, "kind": "Mdef", "node": {".class": "Var", "flags": [], "fullname": "ibis.expr.window.Window._group_by", "name": "_group_by", "type": {".class": "AnyType", "missing_import_name": null, "source_any": null, "type_of_any": 1}}}, "_order_by": {".class": "SymbolTableNode", "implicit": true, "kind": "Mdef", "node": {".class": "Var", "flags": [], "fullname": "ibis.expr.window.Window._order_by", "name": "_order_by", "type": {".class": "AnyType", "missing_import_name": null, "source_any": null, "type_of_any": 1}}}, "_replace": {".class": "SymbolTableNode", "kind": "Mdef", "node": {".class": "FuncDef", "arg_kinds": [0, 4], "arg_names": ["self", "kwds"], "flags": [], "fullname": "ibis.expr.window.Window._replace", "name": "_replace", "type": null}}, "_validate_frame": {".class": "SymbolTableNode", "kind": "Mdef", "node": {".class": "FuncDef", "arg_kinds": [0], "arg_names": ["self"], "flags": [], "fullname": "ibis.expr.window.Window._validate_frame", "name": "_validate_frame", "type": null}}, "bind": {".class": "SymbolTableNode", "kind": "Mdef", "node": {".class": "FuncDef", "arg_kinds": [0, 0], "arg_names": ["self", "table"], "flags": [], "fullname": "ibis.expr.window.Window.bind", "name": "bind", "type": null}}, "combine": {".class": "SymbolTableNode", "kind": "Mdef", "node": {".class": "FuncDef", "arg_kinds": [0, 0], "arg_names": ["self", "window"], "flags": [], "fullname": "ibis.expr.window.Window.combine", "name": "combine", "type": null}}, "equals": {".class": "SymbolTableNode", "kind": "Mdef", "node": {".class": "FuncDef", "arg_kinds": [0, 0, 1], "arg_names": ["self", "other", "cache"], "flags": [], "fullname": "ibis.expr.window.Window.equals", "name": "equals", "type": null}}, "following": {".class": "SymbolTableNode", "implicit": true, "kind": "Mdef", "node": {".class": "Var", "flags": [], "fullname": "ibis.expr.window.Window.following", "name": "following", "type": {".class": "AnyType", "missing_import_name": null, "source_any": null, "type_of_any": 1}}}, "group_by": {".class": "SymbolTableNode", "kind": "Mdef", "node": {".class": "FuncDef", "arg_kinds": [0, 0], "arg_names": ["self", "expr"], "flags": [], "fullname": "ibis.expr.window.Window.group_by", "name": "group_by", "type": null}}, "how": {".class": "SymbolTableNode", "implicit": true, "kind": "Mdef", "node": {".class": "Var", "flags": [], "fullname": "ibis.expr.window.Window.how", "name": "how", "type": {".class": "AnyType", "missing_import_name": null, "source_any": null, "type_of_any": 1}}}, "max_lookback": {".class": "SymbolTableNode", "implicit": true, "kind": "Mdef", "node": {".class": "Var", "flags": [], "fullname": "ibis.expr.window.Window.max_lookback", "name": "max_lookback", "type": {".class": "AnyType", "missing_import_name": null, "source_any": null, "type_of_any": 1}}}, "order_by": {".class": "SymbolTableNode", "kind": "Mdef", "node": {".class": "FuncDef", "arg_kinds": [0, 0], "arg_names": ["self", "expr"], "flags": [], "fullname": "ibis.expr.window.Window.order_by", "name": "order_by", "type": null}}, "preceding": {".class": "SymbolTableNode", "implicit": true, "kind": "Mdef", "node": {".class": "Var", "flags": [], "fullname": "ibis.expr.window.Window.preceding", "name": "preceding", "type": {".class": "AnyType", "missing_import_name": null, "source_any": null, "type_of_any": 1}}}}, "tuple_type": null, "type_vars": [], "typeddict_type": null}}, "__doc__": {".class": "SymbolTableNode", "kind": "Gdef", "node": {".class": "Var", "flags": ["is_ready"], "fullname": "ibis.expr.window.__doc__", "name": "__doc__", "type": "builtins.str"}}, "__file__": {".class": "SymbolTableNode", "kind": "Gdef", "node": {".class": "Var", "flags": ["is_ready"], "fullname": "ibis.expr.window.__file__", "name": "__file__", "type": "builtins.str"}}, "__name__": {".class": "SymbolTableNode", "kind": "Gdef", "node": {".class": "Var", "flags": ["is_ready"], "fullname": "ibis.expr.window.__name__", "name": "__name__", "type": "builtins.str"}}, "__package__": {".class": "SymbolTableNode", "kind": "Gdef", "node": {".class": "Var", "flags": ["is_ready"], "fullname": "ibis.expr.window.__package__", "name": "__package__", "type": "builtins.str"}}, "_choose_non_empty_val": {".class": "SymbolTableNode", "kind": "Gdef", "node": {".class": "FuncDef", "arg_kinds": [0, 0], "arg_names": ["first", "second"], "flags": [], "fullname": "ibis.expr.window._choose_non_empty_val", "name": "_choose_non_empty_val", "type": null}}, "_determine_how": {".class": "SymbolTableNode", "kind": "Gdef", "node": {".class": "FuncDef", "arg_kinds": [0], "arg_names": ["preceding"], "flags": [], "fullname": "ibis.expr.window._determine_how", "name": "_determine_how", "type": null}}, "_sequence_to_tuple": {".class": "SymbolTableNode", "kind": "Gdef", "node": {".class": "FuncDef", "arg_kinds": [0], "arg_names": ["x"], "flags": [], "fullname": "ibis.expr.window._sequence_to_tuple", "name": "_sequence_to_tuple", "type": null}}, "com": {".class": "SymbolTableNode", "cross_ref": "ibis.common.exceptions", "kind": "Gdef"}, "cumulative_window": {".class": "SymbolTableNode", "kind": "Gdef", "node": {".class": "FuncDef", "arg_kinds": [1, 1], "arg_names": ["group_by", "order_by"], "flags": [], "fullname": "ibis.expr.window.cumulative_window", "name": "cumulative_window", "type": null}}, "functools": {".class": "SymbolTableNode", "cross_ref": "functools", "kind": "Gdef"}, "get_preceding_value": {".class": "SymbolTableNode", "kind": "Gdef", "node": {".class": "Decorator", "func": {".class": "FuncDef", "arg_kinds": [0], "arg_names": ["preceding"], "flags": ["is_decorated"], "fullname": "ibis.expr.window.get_preceding_value", "name": "get_preceding_value", "type": null}, "is_overload": false, "var": {".class": "Var", "flags": ["is_ready"], "fullname": null, "name": "get_preceding_value", "type": {".class": "Instance", "args": [{".class": "AnyType", "missing_import_name": null, "source_any": {".class": "AnyType", "missing_import_name": null, "source_any": null, "type_of_any": 1}, "type_of_any": 7}], "type_ref": "functools._SingleDispatchCallable"}}}}, "get_preceding_value_mlb": {".class": "SymbolTableNode", "kind": "Gdef", "node": {".class": "Decorator", "func": {".class": "FuncDef", "arg_kinds": [0], "arg_names": ["preceding"], "flags": ["is_decorated"], "fullname": "ibis.expr.window.get_preceding_value_mlb", "name": "get_preceding_value_mlb", "type": null}, "is_overload": false, "var": {".class": "Var", "flags": ["is_ready"], "fullname": null, "name": "get_preceding_value_mlb", "type": {".class": "CallableType", "arg_kinds": [2, 4], "arg_names": [null, null], "arg_types": [{".class": "AnyType", "missing_import_name": null, "source_any": null, "type_of_any": 2}, {".class": "AnyType", "missing_import_name": null, "source_any": null, "type_of_any": 2}], "bound_args": [], "def_extras": {}, "fallback": "builtins.function", "implicit": false, "is_ellipsis_args": true, "name": "get_preceding_value_mlb", "ret_type": {".class": "AnyType", "missing_import_name": null, "source_any": {".class": "AnyType", "missing_import_name": null, "source_any": null, "type_of_any": 1}, "type_of_any": 7}, "variables": []}}}}, "get_preceding_value_simple": {".class": "SymbolTableNode", "kind": "Gdef", "node": {".class": "Decorator", "func": {".class": "FuncDef", "arg_kinds": [0], "arg_names": ["preceding"], "flags": ["is_decorated"], "fullname": "ibis.expr.window.get_preceding_value_simple", "name": "get_preceding_value_simple", "type": null}, "is_overload": false, "var": {".class": "Var", "flags": ["is_ready"], "fullname": null, "name": "get_preceding_value_simple", "type": {".class": "CallableType", "arg_kinds": [2, 4], "arg_names": [null, null], "arg_types": [{".class": "AnyType", "missing_import_name": null, "source_any": null, "type_of_any": 2}, {".class": "AnyType", "missing_import_name": null, "source_any": null, "type_of_any": 2}], "bound_args": [], "def_extras": {}, "fallback": "builtins.function", "implicit": false, "is_ellipsis_args": true, "name": "get_preceding_value_simple", "ret_type": {".class": "AnyType", "missing_import_name": null, "source_any": {".class": "AnyType", "missing_import_name": null, "source_any": null, "type_of_any": 1}, "type_of_any": 7}, "variables": []}}}}, "get_preceding_value_tuple": {".class": "SymbolTableNode", "kind": "Gdef", "node": {".class": "Decorator", "func": {".class": "FuncDef", "arg_kinds": [0], "arg_names": ["preceding"], "flags": ["is_decorated"], "fullname": "ibis.expr.window.get_preceding_value_tuple", "name": "get_preceding_value_tuple", "type": null}, "is_overload": false, "var": {".class": "Var", "flags": ["is_ready"], "fullname": null, "name": "get_preceding_value_tuple", "type": {".class": "CallableType", "arg_kinds": [2, 4], "arg_names": [null, null], "arg_types": [{".class": "AnyType", "missing_import_name": null, "source_any": null, "type_of_any": 2}, {".class": "AnyType", "missing_import_name": null, "source_any": null, "type_of_any": 2}], "bound_args": [], "def_extras": {}, "fallback": "builtins.function", "implicit": false, "is_ellipsis_args": true, "name": "get_preceding_value_tuple", "ret_type": {".class": "AnyType", "missing_import_name": null, "source_any": {".class": "AnyType", "missing_import_name": null, "source_any": null, "type_of_any": 1}, "type_of_any": 7}, "variables": []}}}}, "ir": {".class": "SymbolTableNode", "cross_ref": "ibis.expr.types", "kind": "Gdef"}, "np": {".class": "SymbolTableNode", "cross_ref": "numpy", "kind": "Gdef"}, "ops": {".class": "SymbolTableNode", "cross_ref": "ibis.expr.operations", "kind": "Gdef"}, "pd": {".class": "SymbolTableNode", "kind": "Gdef", "node": {".class": "Var", "flags": ["is_suppressed_import", "is_ready"], "fullname": "ibis.expr.window.pd", "name": "pd", "type": {".class": "AnyType", "missing_import_name": "ibis.expr.window.pd", "source_any": null, "type_of_any": 3}}}, "propagate_down_window": {".class": "SymbolTableNode", "kind": "Gdef", "node": {".class": "FuncDef", "arg_kinds": [0, 0], "arg_names": ["expr", "window"], "flags": [], "fullname": "ibis.expr.window.propagate_down_window", "name": "propagate_down_window", "type": null}}, "range_window": {".class": "SymbolTableNode", "kind": "Gdef", "node": {".class": "FuncDef", "arg_kinds": [1, 1, 1, 1], "arg_names": ["preceding", "following", "group_by", "order_by"], "flags": [], "fullname": "ibis.expr.window.range_window", "name": "range_window", "type": null}}, "rows_with_max_lookback": {".class": "SymbolTableNode", "kind": "Gdef", "node": {".class": "FuncDef", "arg_kinds": [0, 0], "arg_names": ["rows", "max_lookback"], "flags": [], "fullname": "ibis.expr.window.rows_with_max_lookback", "name": "rows_with_max_lookback", "type": null}}, "trailing_range_window": {".class": "SymbolTableNode", "kind": "Gdef", "node": {".class": "FuncDef", "arg_kinds": [0, 0, 1], "arg_names": ["preceding", "order_by", "group_by"], "flags": [], "fullname": "ibis.expr.window.trailing_range_window", "name": "trailing_range_window", "type": null}}, "trailing_window": {".class": "SymbolTableNode", "kind": "Gdef", "node": {".class": "FuncDef", "arg_kinds": [0, 1, 1], "arg_names": ["preceding", "group_by", "order_by"], "flags": [], "fullname": "ibis.expr.window.trailing_window", "name": "trailing_window", "type": null}}, "util": {".class": "SymbolTableNode", "cross_ref": "ibis.util", "kind": "Gdef"}, "window": {".class": "SymbolTableNode", "kind": "Gdef", "node": {".class": "FuncDef", "arg_kinds": [1, 1, 1, 1], "arg_names": ["preceding", "following", "group_by", "order_by"], "flags": [], "fullname": "ibis.expr.window.window", "name": "window", "type": null}}}, "path": "/home/mgarcia/src/ibis/ibis/expr/window.py"}