{".class": "MypyFile", "_fullname": "ibis.util", "is_partial_stub_package": false, "is_stub": false, "names": {".class": "SymbolTable", "Any": {".class": "SymbolTableNode", "cross_ref": "typing.Any", "kind": "Gdef"}, "Iterator": {".class": "SymbolTableNode", "cross_ref": "typing.Iterator", "kind": "Gdef"}, "List": {".class": "SymbolTableNode", "cross_ref": "typing.List", "kind": "Gdef"}, "Optional": {".class": "SymbolTableNode", "cross_ref": "typing.Optional", "kind": "Gdef"}, "Real": {".class": "SymbolTableNode", "cross_ref": "numbers.Real", "kind": "Gdef"}, "Sequence": {".class": "SymbolTableNode", "cross_ref": "typing.Sequence", "kind": "Gdef"}, "T": {".class": "SymbolTableNode", "kind": "Gdef", "node": {".class": "TypeVarExpr", "fullname": "ibis.util.T", "name": "T", "upper_bound": "builtins.object", "values": [], "variance": 1}}, "Type": {".class": "SymbolTableNode", "cross_ref": "typing.Type", "kind": "Gdef"}, "TypeVar": {".class": "SymbolTableNode", "cross_ref": "typing.TypeVar", "kind": "Gdef"}, "U": {".class": "SymbolTableNode", "kind": "Gdef", "node": {".class": "TypeVarExpr", "fullname": "ibis.util.U", "name": "U", "upper_bound": "builtins.object", "values": [], "variance": 1}}, "Union": {".class": "SymbolTableNode", "cross_ref": "typing.Union", "kind": "Gdef"}, "V": {".class": "SymbolTableNode", "kind": "Gdef", "node": {".class": "TypeVarExpr", "fullname": "ibis.util.V", "name": "V", "upper_bound": "builtins.object", "values": [], "variance": 0}}, "__doc__": {".class": "SymbolTableNode", "kind": "Gdef", "node": {".class": "Var", "flags": ["is_ready"], "fullname": "ibis.util.__doc__", "name": "__doc__", "type": "builtins.str"}}, "__file__": {".class": "SymbolTableNode", "kind": "Gdef", "node": {".class": "Var", "flags": ["is_ready"], "fullname": "ibis.util.__file__", "name": "__file__", "type": "builtins.str"}}, "__name__": {".class": "SymbolTableNode", "kind": "Gdef", "node": {".class": "Var", "flags": ["is_ready"], "fullname": "ibis.util.__name__", "name": "__name__", "type": "builtins.str"}}, "__package__": {".class": "SymbolTableNode", "kind": "Gdef", "node": {".class": "Var", "flags": ["is_ready"], "fullname": "ibis.util.__package__", "name": "__package__", "type": "builtins.str"}}, "adjoin": {".class": "SymbolTableNode", "kind": "Gdef", "node": {".class": "FuncDef", "arg_kinds": [0, 2], "arg_names": ["space", "lists"], "flags": [], "fullname": "ibis.util.adjoin", "name": "adjoin", "type": {".class": "CallableType", "arg_kinds": [0, 2], "arg_names": ["space", "lists"], "arg_types": ["builtins.int", {".class": "Instance", "args": ["builtins.str"], "type_ref": "typing.Sequence"}], "bound_args": [], "def_extras": {"first_arg": null}, "fallback": "builtins.function", "implicit": false, "is_ellipsis_args": false, "name": "adjoin", "ret_type": "builtins.str", "variables": []}}}, "all_of": {".class": "SymbolTableNode", "kind": "Gdef", "node": {".class": "Var", "flags": [], "fullname": "ibis.util.all_of", "name": "all_of", "type": {".class": "AnyType", "missing_import_name": "ibis.util.toolz", "source_any": {".class": "AnyType", "missing_import_name": "ibis.util.toolz", "source_any": null, "type_of_any": 3}, "type_of_any": 7}}}, "any_of": {".class": "SymbolTableNode", "kind": "Gdef", "node": {".class": "Var", "flags": [], "fullname": "ibis.util.any_of", "name": "any_of", "type": {".class": "AnyType", "missing_import_name": "ibis.util.toolz", "source_any": {".class": "AnyType", "missing_import_name": "ibis.util.toolz", "source_any": null, "type_of_any": 3}, "type_of_any": 7}}}, "approx_equal": {".class": "SymbolTableNode", "kind": "Gdef", "node": {".class": "FuncDef", "arg_kinds": [0, 0, 0], "arg_names": ["a", "b", "eps"], "flags": [], "fullname": "ibis.util.approx_equal", "name": "approx_equal", "type": {".class": "CallableType", "arg_kinds": [0, 0, 0], "arg_names": ["a", "b", "eps"], "arg_types": ["numbers.Real", "numbers.Real", "numbers.Real"], "bound_args": [], "def_extras": {"first_arg": null}, "fallback": "builtins.function", "implicit": false, "is_ellipsis_args": false, "name": "approx_equal", "ret_type": {".class": "AnyType", "missing_import_name": null, "source_any": null, "type_of_any": 1}, "variables": []}}}, "collections": {".class": "SymbolTableNode", "cross_ref": "collections", "kind": "Gdef"}, "consume": {".class": "SymbolTableNode", "kind": "Gdef", "node": {".class": "FuncDef", "arg_kinds": [0, 1], "arg_names": ["iterator", "n"], "flags": [], "fullname": "ibis.util.consume", "name": "consume", "type": {".class": "CallableType", "arg_kinds": [0, 1], "arg_names": ["iterator", "n"], "arg_types": [{".class": "Instance", "args": [{".class": "TypeVarType", "fullname": "ibis.util.T", "id": -1, "name": "T", "upper_bound": "builtins.object", "values": [], "variance": 1}], "type_ref": "typing.Iterator"}, {".class": "UnionType", "items": ["builtins.int", {".class": "NoneType"}]}], "bound_args": [], "def_extras": {"first_arg": null}, "fallback": "builtins.function", "implicit": false, "is_ellipsis_args": false, "name": "consume", "ret_type": {".class": "NoneType"}, "variables": [{".class": "TypeVarDef", "fullname": "ibis.util.T", "id": -1, "name": "T", "upper_bound": "builtins.object", "values": [], "variance": 1}]}}}, "convert_unit": {".class": "SymbolTableNode", "kind": "Gdef", "node": {".class": "FuncDef", "arg_kinds": [0, 0, 0, 1], "arg_names": ["value", "unit", "to", "floor"], "flags": [], "fullname": "ibis.util.convert_unit", "name": "convert_unit", "type": null}}, "functools": {".class": "SymbolTableNode", "cross_ref": "functools", "kind": "Gdef"}, "get_logger": {".class": "SymbolTableNode", "kind": "Gdef", "node": {".class": "FuncDef", "arg_kinds": [0, 1, 1, 1], "arg_names": ["name", "level", "format", "propagate"], "flags": [], "fullname": "ibis.util.get_logger", "name": "get_logger", "type": {".class": "CallableType", "arg_kinds": [0, 1, 1, 1], "arg_names": ["name", "level", "format", "propagate"], "arg_types": ["builtins.str", {".class": "UnionType", "items": ["builtins.str", {".class": "NoneType"}]}, {".class": "UnionType", "items": ["builtins.str", {".class": "NoneType"}]}, "builtins.bool"], "bound_args": [], "def_extras": {"first_arg": null}, "fallback": "builtins.function", "implicit": false, "is_ellipsis_args": false, "name": "get_logger", "ret_type": "logging.Logger", "variables": []}}}, "guid": {".class": "SymbolTableNode", "kind": "Gdef", "node": {".class": "FuncDef", "arg_kinds": [], "arg_names": [], "flags": [], "fullname": "ibis.util.guid", "name": "guid", "type": {".class": "CallableType", "arg_kinds": [], "arg_names": [], "arg_types": [], "bound_args": [], "def_extras": {"first_arg": null}, "fallback": "builtins.function", "implicit": false, "is_ellipsis_args": false, "name": "guid", "ret_type": "builtins.str", "variables": []}}}, "indent": {".class": "SymbolTableNode", "kind": "Gdef", "node": {".class": "FuncDef", "arg_kinds": [0, 0], "arg_names": ["text", "spaces"], "flags": [], "fullname": "ibis.util.indent", "name": "indent", "type": {".class": "CallableType", "arg_kinds": [0, 0], "arg_names": ["text", "spaces"], "arg_types": ["builtins.str", "builtins.int"], "bound_args": [], "def_extras": {"first_arg": null}, "fallback": "builtins.function", "implicit": false, "is_ellipsis_args": false, "name": "indent", "ret_type": "builtins.str", "variables": []}}}, "is_function": {".class": "SymbolTableNode", "kind": "Gdef", "node": {".class": "FuncDef", "arg_kinds": [0], "arg_names": ["v"], "flags": [], "fullname": "ibis.util.is_function", "name": "is_function", "type": {".class": "CallableType", "arg_kinds": [0], "arg_names": ["v"], "arg_types": [{".class": "AnyType", "missing_import_name": null, "source_any": null, "type_of_any": 2}], "bound_args": [], "def_extras": {"first_arg": null}, "fallback": "builtins.function", "implicit": false, "is_ellipsis_args": false, "name": "is_function", "ret_type": "builtins.bool", "variables": []}}}, "is_iterable": {".class": "SymbolTableNode", "kind": "Gdef", "node": {".class": "FuncDef", "arg_kinds": [0], "arg_names": ["o"], "flags": [], "fullname": "ibis.util.is_iterable", "name": "is_iterable", "type": {".class": "CallableType", "arg_kinds": [0], "arg_names": ["o"], "arg_types": [{".class": "AnyType", "missing_import_name": null, "source_any": null, "type_of_any": 2}], "bound_args": [], "def_extras": {"first_arg": null}, "fallback": "builtins.function", "implicit": false, "is_ellipsis_args": false, "name": "is_iterable", "ret_type": "builtins.bool", "variables": []}}}, "is_one_of": {".class": "SymbolTableNode", "kind": "Gdef", "node": {".class": "FuncDef", "arg_kinds": [0, 0], "arg_names": ["values", "t"], "flags": [], "fullname": "ibis.util.is_one_of", "name": "is_one_of", "type": {".class": "CallableType", "arg_kinds": [0, 0], "arg_names": ["values", "t"], "arg_types": [{".class": "Instance", "args": [{".class": "TypeVarType", "fullname": "ibis.util.T", "id": -1, "name": "T", "upper_bound": "builtins.object", "values": [], "variance": 1}], "type_ref": "typing.Sequence"}, {".class": "TypeType", "item": {".class": "TypeVarType", "fullname": "ibis.util.U", "id": -2, "name": "U", "upper_bound": "builtins.object", "values": [], "variance": 1}}], "bound_args": [], "def_extras": {"first_arg": null}, "fallback": "builtins.function", "implicit": false, "is_ellipsis_args": false, "name": "is_one_of", "ret_type": {".class": "Instance", "args": ["builtins.bool"], "type_ref": "typing.Iterator"}, "variables": [{".class": "TypeVarDef", "fullname": "ibis.util.T", "id": -1, "name": "T", "upper_bound": "builtins.object", "values": [], "variance": 1}, {".class": "TypeVarDef", "fullname": "ibis.util.U", "id": -2, "name": "U", "upper_bound": "builtins.object", "values": [], "variance": 1}]}}}, "itertools": {".class": "SymbolTableNode", "cross_ref": "itertools", "kind": "Gdef"}, "log": {".class": "SymbolTableNode", "kind": "Gdef", "node": {".class": "FuncDef", "arg_kinds": [0], "arg_names": ["msg"], "flags": [], "fullname": "ibis.util.log", "name": "log", "type": {".class": "CallableType", "arg_kinds": [0], "arg_names": ["msg"], "arg_types": ["builtins.str"], "bound_args": [], "def_extras": {"first_arg": null}, "fallback": "builtins.function", "implicit": false, "is_ellipsis_args": false, "name": "log", "ret_type": {".class": "NoneType"}, "variables": []}}}, "logging": {".class": "SymbolTableNode", "cross_ref": "logging", "kind": "Gdef"}, "operator": {".class": "SymbolTableNode", "cross_ref": "operator", "kind": "Gdef"}, "options": {".class": "SymbolTableNode", "cross_ref": "ibis.config.options", "kind": "Gdef"}, "os": {".class": "SymbolTableNode", "cross_ref": "os", "kind": "Gdef"}, "promote_list": {".class": "SymbolTableNode", "kind": "Gdef", "node": {".class": "FuncDef", "arg_kinds": [0], "arg_names": ["val"], "flags": [], "fullname": "ibis.util.promote_list", "name": "promote_list", "type": {".class": "CallableType", "arg_kinds": [0], "arg_names": ["val"], "arg_types": [{".class": "UnionType", "items": [{".class": "TypeVarType", "fullname": "ibis.util.V", "id": -1, "name": "V", "upper_bound": "builtins.object", "values": [], "variance": 0}, {".class": "Instance", "args": [{".class": "TypeVarType", "fullname": "ibis.util.V", "id": -1, "name": "V", "upper_bound": "builtins.object", "values": [], "variance": 0}], "type_ref": "builtins.list"}]}], "bound_args": [], "def_extras": {"first_arg": null}, "fallback": "builtins.function", "implicit": false, "is_ellipsis_args": false, "name": "promote_list", "ret_type": {".class": "Instance", "args": [{".class": "TypeVarType", "fullname": "ibis.util.V", "id": -1, "name": "V", "upper_bound": "builtins.object", "values": [], "variance": 0}], "type_ref": "builtins.list"}, "variables": [{".class": "TypeVarDef", "fullname": "ibis.util.V", "id": -1, "name": "V", "upper_bound": "builtins.object", "values": [], "variance": 0}]}}}, "safe_index": {".class": "SymbolTableNode", "kind": "Gdef", "node": {".class": "FuncDef", "arg_kinds": [0, 0], "arg_names": ["elements", "value"], "flags": [], "fullname": "ibis.util.safe_index", "name": "safe_index", "type": {".class": "CallableType", "arg_kinds": [0, 0], "arg_names": ["elements", "value"], "arg_types": [{".class": "Instance", "args": ["builtins.int"], "type_ref": "typing.Sequence"}, "builtins.int"], "bound_args": [], "def_extras": {"first_arg": null}, "fallback": "builtins.function", "implicit": false, "is_ellipsis_args": false, "name": "safe_index", "ret_type": "builtins.int", "variables": []}}}, "toolz": {".class": "SymbolTableNode", "kind": "Gdef", "node": {".class": "Var", "flags": ["is_suppressed_import", "is_ready"], "fullname": "ibis.util.toolz", "name": "toolz", "type": {".class": "AnyType", "missing_import_name": "ibis.util.toolz", "source_any": null, "type_of_any": 3}}}, "types": {".class": "SymbolTableNode", "cross_ref": "types", "kind": "Gdef"}, "uuid4": {".class": "SymbolTableNode", "cross_ref": "uuid.uuid4", "kind": "Gdef"}}, "path": "/home/mgarcia/src/ibis/ibis/util.py"}